unstructured_pytesseract/__init__.py
unstructured_pytesseract/pytesseract.py
unstructured.pytesseract-0.3.15.dist-info/LICENSE
unstructured.pytesseract-0.3.15.dist-info/METADATA
unstructured.pytesseract-0.3.15.dist-info/WHEEL
unstructured.pytesseract-0.3.15.dist-info/entry_points.txt
unstructured.pytesseract-0.3.15.dist-info/top_level.txt
unstructured.pytesseract-0.3.15.dist-info/RECORD
