Metadata-Version: 2.1
Name: unstructured.pytesseract
Version: 0.3.15
Summary: Python-tesseract is a python wrapper for Google's Tesseract-OCR
Home-page: https://github.com/madmaze/pytesseract
Author: Samuel Hoffstaetter
Author-email: samuel@hoffstaetter.com
Maintainer: Matthias Lee
Maintainer-email: pytesseract@madmaze.net
License: Apache License 2.0
Keywords: python-tesseract OCR Python
Platform: UNKNOWN
Classifier: License :: OSI Approved :: Apache Software License
Classifier: Programming Language :: Python :: 3
Classifier: Programming Language :: Python :: 3 :: Only
Classifier: Programming Language :: Python :: 3.8
Classifier: Programming Language :: Python :: 3.9
Classifier: Programming Language :: Python :: 3.10
Classifier: Programming Language :: Python :: 3.11
Classifier: Programming Language :: Python :: 3.12
Classifier: Programming Language :: Python :: Implementation :: CPython
Classifier: Programming Language :: Python :: Implementation :: PyPy
Requires-Python: >=3.8
